aurora_neware/__init__.py
aurora_neware/neware.py
aurora_neware/version.py
aurora_neware/cli/__init__.py
aurora_neware/cli/main.py
aurora_neware-0.2.2.dist-info/entry_points.txt
aurora_neware-0.2.2.dist-info/licenses/LICENSE
aurora_neware-0.2.2.dist-info/WHEEL
aurora_neware-0.2.2.dist-info/METADATA
aurora_neware-0.2.2.dist-info/RECORD
