Metadata-Version: 2.4
Name: aurora_neware
Version: 0.2.2
Summary: Python API for Neware Battery Testing System
Requires-Python: >=3.10
Classifier: Development Status :: 3 - Alpha
Classifier: License :: OSI Approved :: MIT License
Classifier: Programming Language :: Python :: 3
Classifier: Operating System :: OS Independent
License-File: LICENSE
Requires-Dist: defusedxml
Requires-Dist: typer
Requires-Dist: bumpver==2024.1130 ; extra == "dev"
Requires-Dist: pre-commit~=4.0 ; extra == "dev"
Requires-Dist: pytest~=8.0 ; extra == "dev"
Provides-Extra: dev
